secret/SCRATCH.py
secret/__init__.py
tests/__init__.py
tests/__main__.py
winter_theme/__init__.py
winter_theme/__main__.py
winter_theme/hooking/__init__.py
winter_theme/hooking/ante_build_hook.py
winter_theme/hooking/ante_release_hook.py
winter_theme/hooking/post_build_hook.py
winter_theme/hooking/post_release_hook.py
winter_theme/pyrustic_data/build_report.json
winter_theme/pyrustic_data/hooking.json
winter_theme/pyrustic_data/hubstore.json
winter_theme/pyrustic_data/release_info.json
winter_theme/pyrustic_data/backstage/data/build_report.json
winter_theme/pyrustic_data/backstage/hooking/build.json
winter_theme/pyrustic_data/backstage/hooking/init.json
winter_theme/pyrustic_data/backstage/hooking/release.json
winter_theme-0.0.4.dist-info/LICENSE
winter_theme-0.0.4.dist-info/METADATA
winter_theme-0.0.4.dist-info/WHEEL
winter_theme-0.0.4.dist-info/entry_points.txt
winter_theme-0.0.4.dist-info/top_level.txt
winter_theme-0.0.4.dist-info/RECORD
