Metadata-Version: 2.1
Name: winter-theme
Version: 0.0.4
Summary: Light theme for Python desktop app
Home-page: https://github.com/pyrustic/winter-theme
Author: Pyrustic Evangelist
Author-email: pyrustic@protonmail.com
Maintainer: Pyrustic Evangelist
Maintainer-email: pyrustic@protonmail.com
License: MIT
Keywords: theme,winter,light-theme,desktop-application
Platform: UNKNOWN
Classifier: Programming Language :: Python :: 3
Classifier: License :: OSI Approved :: MIT License
Classifier: Operating System :: OS Independent
Requires-Python: >=3.5
License-File: LICENSE
Requires-Dist: tkstyle
